pytest_pep8.py
pytest_pycodestyle-1.0.6.dist-info/DESCRIPTION.rst
pytest_pycodestyle-1.0.6.dist-info/METADATA
pytest_pycodestyle-1.0.6.dist-info/RECORD
pytest_pycodestyle-1.0.6.dist-info/WHEEL
pytest_pycodestyle-1.0.6.dist-info/entry_points.txt
pytest_pycodestyle-1.0.6.dist-info/metadata.json
pytest_pycodestyle-1.0.6.dist-info/top_level.txt
