Metadata-Version: 2.0
Name: pytest-pycodestyle
Version: 1.0.6
Summary: pytest plugin to check PEP8 requirements
Home-page: https://bitbucket.org/pytest-dev/pytest-pep8
Author: Holger Krekel and Ronny Pfannschmidt
Author-email: holger.krekel@gmail.com
License: MIT license
Platform: UNKNOWN
Classifier: Programming Language :: Python
Classifier: Programming Language :: Python :: 2.6
Classifier: Programming Language :: Python :: 2.7
Classifier: Programming Language :: Python :: 3.3
Classifier: Programming Language :: Python :: 3.4
Requires-Dist: pycodestyle (>=1.3)
Requires-Dist: pytest (>=2.4.2)
Requires-Dist: pytest-cache
